{
  "appPageId" : "e109cb22-1f24-4b05-910c-50ec24ca8d96",
  "componentName" : "siteforce:sldsOneColLayout",
  "id" : "ee25819a-7a22-453d-8ca6-0778098da4ff",
  "label" : "User Settings",
  "regions" : [ {
    "id" : "441f702b-2d56-4661-a8cd-7dd723a1db7a",
    "regionName" : "header",
    "type" : "region"
  }, {
    "components" : [ {
      "componentAttributes" : {
        "accountSectionTitle" : "Account",
        "accountTabName" : "Account Details",
        "connectedSourcesTabName" : "Connected Sources",
        "emailNotificationsTitle" : "Email Notifications",
        "emailSectionDescText" : "When email notifications are enabled, email me when someone:",
        "hideChatterNotificationSettings" : false,
        "hideConnectedSources" : false,
        "hideEmailNotificationSettings" : false,
        "hideProfileVisibilitySettings" : false,
        "id" : "{!recordId}",
        "locationTitle" : "Location",
        "profileSectionDescText" : "Customize who is able to see what on your profile page",
        "profileSectionToolTipText" : "Restricted: Visible to the employees of the company that created the site. Members: Visible to logged-in members. Public: Visible to anyone viewing pages that don't require login.",
        "profileVisibilityTitle" : "Profile Visibility",
        "settingsPageTitle" : "My Settings"
      },
      "componentName" : "forceCommunity:userSettingsCustomizable",
      "id" : "7d780aa5-5423-432e-b146-5099b16ee2ba",
      "renderPriority" : "NEUTRAL",
      "renditionMap" : { },
      "type" : "component"
    } ],
    "id" : "cb3ee6aa-0a6c-4908-bdd1-ed970fbed8c2",
    "regionName" : "content",
    "type" : "region"
  }, {
    "id" : "3414337b-ef70-4708-8ad4-a355fa604db3",
    "regionName" : "footer",
    "type" : "region"
  } ],
  "themeLayoutType" : "Inner",
  "type" : "view",
  "viewType" : "usersettings"
}