{
  "appPageId" : "c382e4ff-3ea6-4f7e-b22b-7004ff9a29ac",
  "componentName" : "siteforce:dynamicLayout",
  "id" : "55e2d922-6d8b-488f-ad5d-964c5dac4596",
  "label" : "My Account",
  "regions" : [ {
    "id" : "c3481009-72be-4294-8db1-58b851ec05d9",
    "regionName" : "header",
    "type" : "region"
  }, {
    "components" : [ {
      "componentAttributes" : {
        "background" : "background: rgba(0,0,0,0)",
        "backgroundOverlay" : "rgba(0,0,0,0.5)",
        "contentAreaWidth" : 100,
        "sectionConfig" : {
          "UUID" : "20c76203-0e05-481b-846c-2cbd5770cda3",
          "columns" : [ {
            "UUID" : "a681c39d-7854-4211-8405-cd17991f3487",
            "columnKey" : "col1",
            "columnName" : "column 1",
            "columnWidth" : "12",
            "seedComponents" : [ {
              "attributes" : {
                "recordId" : "{!CurrentUser.accountId}",
                "sfdc:identifier" : "forceCommunity_recordHeadline"
              },
              "fqn" : "forceCommunity:recordHeadline"
            }, {
              "attributes" : {
                "recordId" : "{!CurrentUser.accountId}",
                "sfdc:identifier" : "forceCommunity_recordHomeTabs"
              },
              "fqn" : "forceCommunity:recordHomeTabs"
            } ]
          } ]
        },
        "sectionHeight" : 32
      },
      "componentName" : "forceCommunity:section",
      "id" : "20c76203-0e05-481b-846c-2cbd5770cda3",
      "regions" : [ {
        "components" : [ {
          "componentAttributes" : {
            "recordId" : "{!CurrentUser.accountId}"
          },
          "componentName" : "forceCommunity:recordHeadline",
          "id" : "30ca0159-878e-483f-bb8b-e35e771eb0ab",
          "renderPriority" : "NEUTRAL",
          "renditionMap" : { },
          "type" : "component"
        }, {
          "componentAttributes" : {
            "detailsTabLabel" : "Details",
            "discussionsTabLabel" : "Feed",
            "recordId" : "{!CurrentUser.accountId}",
            "relatedTabLabel" : "Related",
            "tab1Type" : "details",
            "tab2Type" : "related",
            "tab3Type" : "chatter",
            "tab4Type" : "none",
            "timelineTabLabel" : "Activity"
          },
          "componentName" : "forceCommunity:recordHomeTabs",
          "id" : "48c9154c-5cbe-4038-9af8-aff26a8c4cc0",
          "renderPriority" : "NEUTRAL",
          "renditionMap" : { },
          "type" : "component"
        } ],
        "id" : "a681c39d-7854-4211-8405-cd17991f3487",
        "regionLabel" : "column 1",
        "regionName" : "col1",
        "renditionMap" : { },
        "type" : "region"
      } ],
      "renderPriority" : "NEUTRAL",
      "renditionMap" : { },
      "type" : "component"
    } ],
    "id" : "b743d695-2b0a-4c31-b957-032aa9ec7c4b",
    "regionName" : "content",
    "type" : "region"
  }, {
    "id" : "cd597658-b22f-4404-8650-6260f0807007",
    "regionName" : "footer",
    "type" : "region"
  } ],
  "themeLayoutType" : "Inner",
  "type" : "view",
  "viewType" : "my-account"
}